paynlsdk/__init__.py
paynlsdk/exceptions.py
paynlsdk/objects.py
paynlsdk/validators.py
paynlsdk/api/__init__.py
paynlsdk/api/client.py
paynlsdk/api/requestbase.py
paynlsdk/api/responsebase.py
paynlsdk/api/refund/__init__.py
paynlsdk/api/refund/info.py
paynlsdk/api/refund/transaction.py
paynlsdk/api/transaction/__init__.py
paynlsdk/api/transaction/approve.py
paynlsdk/api/transaction/capture.py
paynlsdk/api/transaction/decline.py
paynlsdk/api/transaction/getbanks.py
paynlsdk/api/transaction/getservice.py
paynlsdk/api/transaction/getservicepaymentoptions.py
paynlsdk/api/transaction/info.py
paynlsdk/api/transaction/refund.py
paynlsdk/api/transaction/start.py
paynlsdk/api/transaction/status.py
paynlsdk/api/transaction/voidauthorization.py
paynlsdk/api/validate/__init__.py
paynlsdk/api/validate/payserverip.py
paynlsdk/client/__init__.py
paynlsdk/client/banks.py
paynlsdk/client/paymentmethods.py
paynlsdk/client/refund.py
paynlsdk/client/transaction.py
paynlsdk/client/validate.py
paynlsdk/enums/__init__.py
paynlsdk/enums/enums.py
paynlsdk-1.0.3.dist-info/LICENSE.md
paynlsdk-1.0.3.dist-info/METADATA
paynlsdk-1.0.3.dist-info/WHEEL
paynlsdk-1.0.3.dist-info/top_level.txt
paynlsdk-1.0.3.dist-info/RECORD
