Metadata-Version: 2.1
Name: paynlsdk
Version: 1.0.3
Summary: PayNL SDK
Home-page: https://github.com/paynl/python-sdk
Author: Ing. R.J. van Dongen
Author-email: rogier@sebsoft.nl
License: UNKNOWN
Project-URL: Bug Reports, https://github.com/paynl/python-sdk/issues
Project-URL: Source, https://github.com/paynl/python-sdk/
Keywords: PAYNL,SDK,Python
Platform: UNKNOWN
Classifier: Programming Language :: Python :: 3.7
Classifier: License :: OSI Approved :: MIT License
Classifier: Operating System :: OS Independent
Classifier: Development Status :: 4 - Beta
Classifier: Intended Audience :: Developers
Classifier: Topic :: Software Development :: Libraries :: Python Modules
Requires-Dist: marshmallow (<3,>=2)
Requires-Dist: requests
